{
  "name": "cloudexperiencehostcommon.dll",
  "loaded_by": [
    {
      "name": "explorer.exe",
      "weight": "rare",
      "pct": 8.7,
      "lolbin": true
    },
    {
      "name": "msedge.exe",
      "weight": "rare",
      "pct": 1.6,
      "lolbin": true
    },
    {
      "name": "runtimebroker.exe",
      "weight": "rare",
      "pct": 7.8,
      "lolbin": false
    },
    {
      "name": "sihost.exe",
      "weight": "uncommon",
      "pct": 25,
      "lolbin": false
    },
    {
      "name": "taskhostw.exe",
      "weight": "rare",
      "pct": 8.5,
      "lolbin": false
    }
  ]
}
