{
  "name": "vcruntime140_1_clr0400.dll",
  "loaded_by": [
    {
      "name": "mscorsvw.exe",
      "weight": "common",
      "pct": 66.5,
      "lolbin": false
    },
    {
      "name": "ngen.exe",
      "weight": "common",
      "pct": 54.3,
      "lolbin": true
    },
    {
      "name": "ngentask.exe",
      "weight": "uncommon",
      "pct": 25,
      "lolbin": false
    },
    {
      "name": "powershell.exe",
      "weight": "common",
      "pct": 66.7,
      "lolbin": false
    },
    {
      "name": "taskhostw.exe",
      "weight": "rare",
      "pct": 2.8,
      "lolbin": false
    }
  ]
}
